setup.cfg
setup.py
pycda/__init__.py
pycda/classifiers.py
pycda/detectors.py
pycda/error_stats.py
pycda/extractors.py
pycda/predictions.py
pycda/sample_data.py
pycda/util_functions.py
pycda.egg-info/PKG-INFO
pycda.egg-info/SOURCES.txt
pycda.egg-info/dependency_links.txt
pycda.egg-info/requires.txt
pycda.egg-info/top_level.txt
pycda/models/classifier_12x12_2.h5
pycda/models/tinynet.h5
pycda/models/unet.h5
pycda/sample_imgs/holdout_tile.pgm
pycda/sample_imgs/holdout_tile_labels.csv
pycda/sample_imgs/mercury.png
pycda/sample_imgs/rgb_sample.jpg
pycda/sample_imgs/selection0.png
pycda/sample_imgs/selection2.png
pycda/sample_imgs/selection3.png
pycda/sample_imgs/selection4.png
pycda/sample_imgs/selection5.png