Metadata-Version: 1.1
Name: pycda
Version: 0.1.14
Summary: Python Crater Detection Algorithm (PyCDA) is a pipeline for crater detection; go from image to annotated crater stats in minutes.
Home-page: https://github.com/AlliedToasters/PyCDA
Author: Michael Klear
Author-email: michael.klear@colorado.edu
License: MIT
Download-URL: https://github.com/AlliedToasters/PyCDA/archive/0.1.14.tar.gz
Keywords: crater detection,astronomy,planetary science,planetary geology
Platform: UNKNOWN
